sorting_joany_h_k/__init__.py
sorting_joany_h_k/bubble_sort.py
sorting_joany_h_k/insertion_sort.py
sorting_joany_h_k/quick_sort.py
sorting_joany_h_k/selection_sort.py
sorting_joany_h_k-0.1.dist-info/METADATA
sorting_joany_h_k-0.1.dist-info/WHEEL
sorting_joany_h_k-0.1.dist-info/top_level.txt
sorting_joany_h_k-0.1.dist-info/RECORD
