Metadata-Version: 2.1
Name: sorting-joany-h-k
Version: 0.1
Summary: Sorting algorithm from Propulsion
Home-page: http://github.com/storborg/funniest
Author: J. Hernandez
Author-email: joany.hernandez.kong@gmail.com
License: MIT
Platform: UNKNOWN
